direct_formatting_pandas_ods_reader/__init__.py
direct_formatting_pandas_ods_reader/__main__.py
direct_formatting_pandas_ods_reader/ods_reader.py
direct_formatting_pandas_ods_reader/xml_utils.py
direct_formatting_pandas_ods_reader-0.5.3.dist-info/licenses/LICENSE.txt
direct_formatting_pandas_ods_reader-0.5.3.dist-info/METADATA
direct_formatting_pandas_ods_reader-0.5.3.dist-info/WHEEL
direct_formatting_pandas_ods_reader-0.5.3.dist-info/entry_points.txt
direct_formatting_pandas_ods_reader-0.5.3.dist-info/top_level.txt
direct_formatting_pandas_ods_reader-0.5.3.dist-info/RECORD
