Metadata-Version: 2.4
Name: direct-formatting-pandas-ods-reader
Version: 0.5.3
Summary: Read ODS files into a pandas DataFrame while preserving direct formatting (strong, emphasis, underline, superscript, subscript, and anchors) as markup (AsciiDoc, Markdown, HTML).
Author-email: Yann Trividic <bonjour@yanntrividic.fr>
License:                     GNU GENERAL PUBLIC LICENSE
Project-URL: Homepage, https://gitlab.com/yanntrividic/direct-formatting-pandas-ods-reader
Project-URL: Bug Tracker, https://gitlab.com/yanntrividic/direct-formatting-pandas-ods-reader/-/issues
Keywords: pandas,ods,spreadsheet,direct,formatting,reader
Requires-Python: >=3.8
License-File: LICENSE.txt
Requires-Dist: pandas>=2.0
Requires-Dist: lxml>=6.0
Dynamic: license-file
